{"Code":"ALP.FTH.021","Name":"Come to Her, Stay with Her","Rank":2.0,"Type":"Response","Class":"","Attribute":"Faith","Cost":"2","Power":"","Life":"","Hand":"","Text":"<b>Trigger:<\/b> Target reinforcement is activated by a card arriving to its fortification.\n<b>Response:<\/b> Target reinforcement gains the <b>Persistence, 1<\/b> keyword. \n(<b>Persistence, 1<\/b> <i>(This card is not destroyed after activation. When this card is revealed, it gains 1 Persist counter(s). In the end phase of your turn, remove 1 Persist counter from this card or destroy it.)<\/i>)"}